mod_tbl_linebuilder/__init__.py
mod_tbl_linebuilder/lines.py
mod_tbl_linebuilder/styles.py
mod_tbl_linebuilder-0.0.5.dist-info/DESCRIPTION.rst
mod_tbl_linebuilder-0.0.5.dist-info/METADATA
mod_tbl_linebuilder-0.0.5.dist-info/RECORD
mod_tbl_linebuilder-0.0.5.dist-info/WHEEL
mod_tbl_linebuilder-0.0.5.dist-info/metadata.json
mod_tbl_linebuilder-0.0.5.dist-info/top_level.txt
