Metadata-Version: 2.0
Name: mod-tbl-linebuilder
Version: 0.0.5
Summary: library for building line level components of a table - intended to be used as a sub-component of a full featured table constructor
Home-page: https://github.com/TravisLazar/travs-table-linebuilder
Author: Travis Lazar
Author-email: travis.lazar@gmail.com
License: GPLv3
Platform: UNKNOWN
Classifier: Programming Language :: Python :: 3
Requires-Dist: utflib
